retworkx/__init__.py
retworkx/namespace.py
retworkx-0.17.1.dist-info/METADATA
retworkx-0.17.1.dist-info/WHEEL
retworkx-0.17.1.dist-info/top_level.txt
retworkx-0.17.1.dist-info/RECORD
