Metadata-Version: 2.1
Name: retworkx
Version: 0.17.1
Summary: A High-Performance Graph Library for Python
Author: Matthew Treinish
Author-email: mtreinish@kortar.org
License: Apache-2.0
Project-URL: issues, https://github.com/Qiskit/rustworkx/issues
Project-URL: source, https://github.com/Qiskit/rustworkx
Project-URL: documentation, https://www.rustworkx.org/
Project-URL: releasenotes, https://www.rustworkx.org/release_notes.html
Keywords: Networks,Network,Graph,Graph Theory,DAG
Classifier: Intended Audience :: Developers
Classifier: Intended Audience :: Science/Research
Classifier: Programming Language :: Rust
Classifier: Programming Language :: Python :: 3 :: Only
Classifier: Programming Language :: Python :: 3.9
Classifier: Programming Language :: Python :: 3.10
Classifier: Programming Language :: Python :: 3.11
Classifier: Programming Language :: Python :: 3.12
Classifier: Programming Language :: Python :: 3.13
Classifier: Operating System :: MacOS :: MacOS X
Classifier: Operating System :: Microsoft :: Windows
Classifier: Operating System :: POSIX :: Linux
Requires-Python: >=3.9
Requires-Dist: rustworkx
Provides-Extra: all
Requires-Dist: matplotlib>=3.0; extra == "all"
Requires-Dist: pillow>=5.4; extra == "all"
Provides-Extra: graphviz
Requires-Dist: pillow>=5.4; extra == "graphviz"
Provides-Extra: mpl
Requires-Dist: matplotlib>=3.0; extra == "mpl"
